{
  "battlefield_id": "redstone_town_alley",
  "name": "Dark Alley",
  "tileset": "urban_alley",
  "description": "A narrow alley between buildings. Crates and debris provide cover, but limit movement.",
  "dimensions": {
    "width": 7,
    "height": 12
  },
  "tile_size": 48,
  "terrain": {
    "default": "cobblestone",
    "walls": [
      [0, 0, 6, 0],
      [0, 11, 6, 11],
      [0, 0, 0, 11],
      [6, 0, 6, 11]
    ],
    "obstacles": [
      {"type": "crate", "position": [5, 1], "blocks_movement": true, "blocks_sight": false, "cover_value": 1},
      {"type": "barrel", "position": [1, 2], "blocks_movement": true, "blocks_sight": false, "cover_value": 1},
      {"type": "barrel", "position": [1, 3], "blocks_movement": true, "blocks_sight": false, "cover_value": 1},
      {"type": "debris", "position": [5, 4], "blocks_movement": true, "blocks_sight": false, "cover_value": 0},
      {"type": "crate", "position": [5, 7], "blocks_movement": true, "blocks_sight": false, "cover_value": 1},
      {"type": "crate", "position": [2, 5], "blocks_movement": true, "blocks_sight": false, "cover_value": 1},
      {"type": "barrel", "position": [1, 7], "blocks_movement": true, "blocks_sight": false, "cover_value": 1}
    ]
  },
  "spawn_zones": {
    "player_start": [
      [1, 9], [1, 10], [2, 9], [2, 8]
    ],
    "enemy_spawns": [
      [4, 1]
    ],
    "exit_point": [1, 7]
  },
  "lighting": "dark",
  "environmental_effects": [
    {"type": "shadows", "effect": "reduced_visibility"}
  ]
}